fastsim-3.0.6.dist-info/RECORD
fastsim-3.0.6.dist-info/WHEEL
fastsim-3.0.6.dist-info/METADATA
fastsim-3.0.6.dist-info/licenses/LICENSE.md
fastsim-3.0.6.dist-info/licenses/LICENSE
fastsim/copy_stub_docstrings.py
fastsim/fastsim.cpython-311-darwin.so
fastsim/__init__.py
fastsim/pymoo_api.py
fastsim/fastsim.pyi
fastsim/tests/test_resources.py
fastsim/tests/test_utils.py
fastsim/tests/test_speedup.py
fastsim/tests/test_serde.py
fastsim/utils/__init__.py
fastsim/utils/utilities.py
fastsim/demos/demo_hev_thrml_cs_ca.py
fastsim/demos/demo_hev_thrml_ws_ca.py
fastsim/demos/demo_hev_thrml_ws_wa.py
fastsim/demos/demo_bev_thrml_ws_wa.py
fastsim/demos/__init__.py
fastsim/demos/demo_bev_thrml_ws_ca.py
fastsim/demos/demo_bev_thrml_cs_ca.py
fastsim/demos/.gitignore
fastsim/demos/demo_cavs.py
fastsim/demos/demo_hev.py
fastsim/demos/plot_utils.py
fastsim/demos/demo_bev_thrml_sweep.py
fastsim/demos/demo_conv.py
fastsim/demos/test_demos.py
fastsim/demos/demo_trace_miss.py
fastsim/demos/demo_bev.py
