Metadata-Version: 2.4
Name: fastsim
Version: 3.0.6
Classifier: Programming Language :: Python :: 3
Classifier: License :: Other/Proprietary License
Classifier: Operating System :: POSIX
Classifier: Operating System :: MacOS :: MacOS X
Classifier: Operating System :: Microsoft :: Windows
Requires-Dist: pandas>=2.1.2
Requires-Dist: polars~=1.4
Requires-Dist: matplotlib~=3.3
Requires-Dist: numpy>=1.18,<=2.3.2
Requires-Dist: seaborn>=0.11.0,<13.2
Requires-Dist: typing-extensions~=4.12
Requires-Dist: pyyaml==6.0.2
Requires-Dist: msgpack==1.1.0
Requires-Dist: ipykernel~=6.29
Requires-Dist: executing~=2.0
Requires-Dist: pip
Requires-Dist: types-seaborn~=0.13.2
Requires-Dist: pylsp-mypy>=0.7.0 ; extra == 'dev'
Requires-Dist: pylsp-rope>=0.1.17 ; extra == 'dev'
Requires-Dist: ruff>=0.11.9 ; extra == 'dev'
Requires-Dist: pytest~=8.3 ; extra == 'dev'
Requires-Dist: maturin~=1.8 ; extra == 'dev'
Requires-Dist: python-lsp-server~=1.10 ; extra == 'dev'
Requires-Dist: memory-profiler~=0.61.0 ; extra == 'dev'
Requires-Dist: pymoo~=0.6 ; extra == 'dev'
Requires-Dist: plotly~=6.0 ; extra == 'dev'
Requires-Dist: deepdiff>=8.4.2 ; extra == 'dev'
Provides-Extra: dev
License-File: LICENSE.md
License-File: LICENSE
Summary: Tool for modeling vehicle powertrains
Author-email: NREL/MTES/CIMS/MBAP Group <fastsim@nrel.gov>
Requires-Python: >=3.10, <3.13
Project-URL: Homepage, https://www.nrel.gov/transportation/fastsim.html
